gopest/__init__.py
gopest/_version.py
gopest/check_slaves.py
gopest/commands.py
gopest/common.py
gopest/make_case_pst.py
gopest/obs.py
gopest/obs_def.py
gopest/par.py
gopest/par_def.py
gopest/pest_model.py
gopest/rename_latest_files.py
gopest/run_beopest.py
gopest/run_ns_pr.py
gopest/submit_beopest.py
gopest/data/case.pst
gopest/data/goPESTconfig.aut2.toml
gopest/data/goPESTconfig.toml
gopest/data/goPESTobs.list
gopest/data/goPESTpar.list
gopest/utils/__init__.py
gopest/utils/gener_groups.py
gopest/utils/t2listingh5.py
gopest/utils/waiwera_listing.py
gopest-0.0.14.dist-info/licenses/LICENSE
gopest-0.0.14.dist-info/METADATA
gopest-0.0.14.dist-info/WHEEL
gopest-0.0.14.dist-info/entry_points.txt
gopest-0.0.14.dist-info/top_level.txt
gopest-0.0.14.dist-info/RECORD
