Metadata-Version: 2.4
Name: goPEST
Version: 0.0.14
Summary: A TOUGH2/Waiwera interface to PEST
Author-email: Angus Yeh <a.yeh@auckland.ac.nz>
License: BSD 3-Clause License
Keywords: goPEST,PEST,Waiwera,TOUGH2,AUTOUGH2
Classifier: Development Status :: 2 - Pre-Alpha
Classifier: Environment :: Console
Classifier: License :: OSI Approved :: BSD License
Classifier: Topic :: Scientific/Engineering
Classifier: Programming Language :: Python :: 3
Requires-Python: >=2.7
License-File: LICENSE
Requires-Dist: PyTOUGH
Requires-Dist: gimu
Requires-Dist: numpy
Requires-Dist: scipy
Requires-Dist: h5py
Requires-Dist: pyyaml
Requires-Dist: tomlkit
Requires-Dist: xlwt
Requires-Dist: setuptools_scm
Dynamic: license-file
